orbis_plugin_aggregation_weblyzard_harvest/__init__.py
orbis_plugin_aggregation_weblyzard_harvest/main.py
orbis_plugin_aggregation_weblyzard_harvest-2.2.4.dist-info/LICENSE
orbis_plugin_aggregation_weblyzard_harvest-2.2.4.dist-info/METADATA
orbis_plugin_aggregation_weblyzard_harvest-2.2.4.dist-info/WHEEL
orbis_plugin_aggregation_weblyzard_harvest-2.2.4.dist-info/top_level.txt
orbis_plugin_aggregation_weblyzard_harvest-2.2.4.dist-info/RECORD
