Metadata-Version: 2.1
Name: orbis-plugin-aggregation-weblyzard-harvest
Version: 2.2.4
Summary: The Weblyzard Harvest aggregation plugin for Orbis
Home-page: https://github.com/orbis-eval/orbis_plugin_aggregation_weblyzard_harvest
Author: fabod
License: GPL2
Platform: UNKNOWN
Requires-Python: >3.6
